singlecase/__init__.py
singlecase/data/__init__.py
singlecase/effectsize/__init__.py
singlecase/permtest/__init__.py
singlecase/plotting/__init__.py
singlecase/table/__init__.py
singlecase-0.2.2.dist-info/LICENSE
singlecase-0.2.2.dist-info/METADATA
singlecase-0.2.2.dist-info/WHEEL
singlecase-0.2.2.dist-info/top_level.txt
singlecase-0.2.2.dist-info/RECORD
